{ 
	"order": 2, 

	"navEntry": { 
		"label": "About", 
		"targetSectionSelector": "#about-section"
	}, 

	"sectionID": "about-section", 

	"head": { 
		"subheading": "A few words", 
		
		"heading": "About Me", 

		"paragraphs": [ 
			{ 
				"text": "I am a self taught artist and I love to paint things that take me to a strange and colourful world. This is my way to express myself and in every painting I create I put a little piece of my heart and my colourful thoughts." 
			} 
		], 

		"image": { 
			"src": "303-3035876_transparent-sexy-woman-silhouette-png-transparent-elegant-woman-color.png" 

		}
	}, 

	"body": [ 
		{ 
			"heading": "Life", 
			"paragraphs": [ 
				{ 
					"text": "Coming Soon" 
				} 
			], 
	
			"image": { 
				"src": "303-3035876_transparent-sexy-woman-silhouette-png-transparent-elegant-woman.png" 
	
			}
		}, 

		{ 
			"heading": "Interests", 
			"paragraphs": [ 
				{ 
					"text": "Coming Soon" 
				} 
			], 
	
			"image": { 
				"src": "303-3035876_transparent-sexy-woman-silhouette-png-transparent-elegant-woman.png" 
	
			}
		}, 

		{
			"heading": "Hobbies", 
			"paragraphs": [ 
				{ 
					"text": "Coming Soon" 
				}
			], 
	
			"image": { 
				"src": "303-3035876_transparent-sexy-woman-silhouette-png-transparent-elegant-woman.png" 
	
			}
		}

	]

}